FBX2glTF/conanfile.py
fbx2glb/__init__.py
fbx2glb/batch.py
fbx2glb/cli.py
fbx2glb/component.py
fbx2glb/converter.py
fbx2glb/fbx_upgrader.py
fbx2glb/params.py
fbx2glb/utils.py
fbx2glb-0.1.0.dist-info/licenses/LICENSE
tests/__init__.py
tests/test_init.py
tests/test_utils.py
fbx2glb-0.1.0.dist-info/METADATA
fbx2glb-0.1.0.dist-info/WHEEL
fbx2glb-0.1.0.dist-info/entry_points.txt
fbx2glb-0.1.0.dist-info/top_level.txt
fbx2glb-0.1.0.dist-info/RECORD
