Metadata-Version: 2.4
Name: fbx2glb
Version: 0.1.0
Summary: Convert FBX files to GLB format for web-based 3D applications
Author-email: Ge Yang <ge.ike.yang@gmail.com>
License-Expression: MIT
Project-URL: Homepage, https://github.com/vuer-ai/fbx2glb
Project-URL: Bug Tracker, https://github.com/vuer-ai/fbx2glb/issues
Classifier: Programming Language :: Python :: 3
Classifier: Operating System :: OS Independent
Classifier: Topic :: Multimedia :: Graphics :: 3D Modeling
Classifier: Topic :: Scientific/Engineering :: Visualization
Requires-Python: >=3.7
License-File: LICENSE
Requires-Dist: numpy>=1.20.0
Provides-Extra: fbxsdk
Provides-Extra: blender
Provides-Extra: dev
Requires-Dist: pytest>=7.0.0; extra == "dev"
Requires-Dist: black>=22.0.0; extra == "dev"
Requires-Dist: isort>=5.10.0; extra == "dev"
Requires-Dist: mypy>=0.940; extra == "dev"
Requires-Dist: twine>=4.0.0; extra == "dev"
Dynamic: license-file
